mcard/__init__.py
mcard/api.py
mcard/cli.py
mcard/file_io.py
mcard/loader.py
mcard/config/__init__.py
mcard/config/config_constants.py
mcard/config/env_parameters.py
mcard/config/improved_logging.py
mcard/config/logging.py
mcard/config/logging_config.py
mcard/config/settings.py
mcard/engine/__init__.py
mcard/engine/base.py
mcard/engine/sqlite_engine.py
mcard/model/__init__.py
mcard/model/card.py
mcard/model/card_collection.py
mcard/model/compatibility.py
mcard/model/dots.py
mcard/model/event_producer.py
mcard/model/g_time.py
mcard/model/handle.py
mcard/model/interpreter.py
mcard/model/pagination.py
mcard/model/pcard.py
mcard/model/schema.py
mcard/model/vcard.py
mcard/model/vcard_vocabulary.py
mcard/model/detectors/__init__.py
mcard/model/detectors/base_detector.py
mcard/model/detectors/binary_detector.py
mcard/model/detectors/data_format_detectors.py
mcard/model/detectors/language_detector.py
mcard/model/detectors/markup_detectors.py
mcard/model/detectors/obj_detector.py
mcard/model/detectors/python_detector.py
mcard/model/detectors/registry.py
mcard/model/detectors/text_format_detector.py
mcard/model/hash/__init__.py
mcard/model/hash/constants.py
mcard/model/hash/enums.py
mcard/model/hash/validator.py
mcard/model/hash/algorithms/__init__.py
mcard/model/hash/algorithms/custom_hash.py
mcard/model/hash/algorithms/local_sha256.py
mcard/model/strategies/__init__.py
mcard/model/strategies/detection_strategy.py
mcard/model/utils/__init__.py
mcard/model/utils/content_analyzer.py
mcard/model/validators/__init__.py
mcard/model/validators/base_validator.py
mcard/model/validators/binary_validator.py
mcard/model/validators/text_validator.py
mcard/model/validators/validation_registry.py
mcard/model/vcard_ext/__init__.py
mcard/model/vcard_ext/core.py
mcard/model/vcard_ext/network.py
mcard/model/vcard_ext/observability.py
mcard/model/vcard_ext/storage.py
mcard/model/vcard_ext/vendors.py
mcard/ptr/__init__.py
mcard/ptr/cli.py
mcard/ptr/runner.py
mcard/ptr/clm/__init__.py
mcard-0.1.48.dist-info/METADATA
mcard-0.1.48.dist-info/WHEEL
mcard-0.1.48.dist-info/entry_points.txt
mcard-0.1.48.dist-info/top_level.txt
mcard-0.1.48.dist-info/RECORD
