Metadata-Version: 2.4
Name: mcard
Version: 0.1.48
Summary: MCard: Local-first Content Addressable Storage with Content Type Detection
Home-page: https://github.com/xlp0/MCard_TDD
Author: Ben Koo
Author-email: Ben Koo <koo0905@gmail.com>
Project-URL: Homepage, https://github.com/xlp0/MCard_TDD
Project-URL: Source, https://github.com/xlp0/MCard_TDD
Project-URL: Tracker, https://github.com/xlp0/MCard_TDD/issues
Classifier: Development Status :: 3 - Alpha
Classifier: Intended Audience :: Developers
Classifier: License :: OSI Approved :: MIT License
Classifier: Programming Language :: Python :: 3
Classifier: Programming Language :: Python :: 3.10
Classifier: Programming Language :: Python :: 3.11
Classifier: Programming Language :: Python :: 3.12
Requires-Python: >=3.9
Requires-Dist: python-dateutil>=2.9.0.post0
Requires-Dist: SQLAlchemy>=1.4.47
Requires-Dist: aiosqlite>=0.17.0
Requires-Dist: aiohttp>=3.9.0
Requires-Dist: python-dotenv>=1.1.0
Requires-Dist: chardet>=5.1.0
Requires-Dist: structlog>=23.2.0
Requires-Dist: python-json-logger>=3.0.0
Requires-Dist: colorlog>=6.7.0
Requires-Dist: PyYAML>=6.0.0
Requires-Dist: wasmtime>=39.0.0
Requires-Dist: websockets>=12.0
Provides-Extra: xml
Requires-Dist: lxml>=4.9.0; extra == "xml"
Provides-Extra: qnlp
Requires-Dist: lambeq>=0.4.2; extra == "qnlp"
Requires-Dist: torch>=2.0.0; extra == "qnlp"
Provides-Extra: observability
Requires-Dist: opentelemetry-sdk>=1.20.0; extra == "observability"
Requires-Dist: opentelemetry-exporter-otlp>=1.20.0; extra == "observability"
Requires-Dist: opentelemetry-instrumentation>=0.41b0; extra == "observability"
Provides-Extra: dev
Requires-Dist: pytest<9,>=8.2.0; extra == "dev"
Requires-Dist: pytest-asyncio>=0.23.8; extra == "dev"
Requires-Dist: pytest-cov>=4.1.0; extra == "dev"
Requires-Dist: mypy>=1.7.1; extra == "dev"
Requires-Dist: black>=23.11.0; extra == "dev"
Requires-Dist: isort>=5.12.0; extra == "dev"
Requires-Dist: twine>=6.1.0; extra == "dev"
Requires-Dist: lxml>=4.9.0; extra == "dev"
Requires-Dist: pre-commit>=3.0.0; extra == "dev"
Requires-Dist: ruff>=0.1.0; extra == "dev"
Dynamic: author
Dynamic: home-page
Dynamic: requires-python
